BcryptRpcServer.py
burpextender_pb2.py
burpextender_pb2_grpc.py
BcryptRpcServer-0.0.6.dist-info/METADATA
BcryptRpcServer-0.0.6.dist-info/WHEEL
BcryptRpcServer-0.0.6.dist-info/top_level.txt
BcryptRpcServer-0.0.6.dist-info/RECORD
