Metadata-Version: 2.1
Name: BcryptRpcServer
Version: 0.0.6
Summary: The rpc server api of https://github.com/cyal1/BcryptMontoya
Home-page: https://github.com/cyal1/BcryptRpcServer/tree/main/python
Author: cyal1
Author-email: admin@example.com
Requires-Dist: grpcio-tools (==1.54.2)
Requires-Dist: grpcio (==1.54.2)
Requires-Dist: protobuf (==4.23.2)
